pyStandardSettings/__init__.py
pyStandardSettings/helpers.py
pyStandardSettings/pyStandardSettings.py
pyStandardSettings-0.0.1.dist-info/DESCRIPTION.rst
pyStandardSettings-0.0.1.dist-info/METADATA
pyStandardSettings-0.0.1.dist-info/RECORD
pyStandardSettings-0.0.1.dist-info/WHEEL
pyStandardSettings-0.0.1.dist-info/metadata.json
pyStandardSettings-0.0.1.dist-info/top_level.txt
