Metadata-Version: 2.0
Name: pyStandardSettings
Version: 0.0.1
Summary: Standardised settings loader
Home-page: https://github.com/soixantecircuits/pyStandardSettings
Author: Soixante circuits
Author-email: emmanuel@soixantecircuits.fr
License: MIT
Keywords: argv env settings config commandline arguments conf file json
Platform: UNKNOWN
Classifier: Development Status :: 3 - Alpha
Classifier: Intended Audience :: Developers
Classifier: Topic :: System :: Installation/Setup
Classifier: Topic :: Utilities
Classifier: License :: OSI Approved :: MIT License
Classifier: Programming Language :: Python :: 2
Classifier: Programming Language :: Python :: 2.7
Requires-Dist: dotmap (>=1.2.17)
Provides-Extra: dev
Provides-Extra: test
Requires-Dist: mock (>=1.0.1); extra == 'test'
